groufi/__init__.py
groufi/group_permutation.py
groufi-0.0.3.dist-info/LICENSE
groufi-0.0.3.dist-info/WHEEL
groufi-0.0.3.dist-info/METADATA
groufi-0.0.3.dist-info/RECORD
