Metadata-Version: 2.1
Name: groufi
Version: 0.0.3
Summary: A small library to compute group feature importance
Home-page: https://github.com/BorealisAI/group-feature-importance
License: Attribution-NonCommercial-ShareAlike 4.0 International
Keywords: ML,explainability,sklearn,feature importance
Author: Borealis AI
Maintainer: Thibaut Durand
Maintainer-email: durand.tibo+gh@gmail.com
Requires-Python: >=3.8,<4.0
Classifier: Development Status :: 4 - Beta
Classifier: Intended Audience :: Developers
Classifier: Intended Audience :: Science/Research
Classifier: License :: Free for non-commercial use
Classifier: License :: Other/Proprietary License
Classifier: Operating System :: POSIX :: Linux
Classifier: Programming Language :: Python :: 3
Classifier: Programming Language :: Python :: 3.8
Classifier: Programming Language :: Python :: 3.9
Classifier: Programming Language :: Python :: 3.10
Classifier: Programming Language :: Python :: 3.11
Classifier: Programming Language :: Python :: 3.10
Classifier: Programming Language :: Python :: 3.8
Classifier: Programming Language :: Python :: 3.9
Classifier: Topic :: Scientific/Engineering :: Artificial Intelligence
Requires-Dist: numpy (>=1.22.2,<2.0.0)
Requires-Dist: pandas (>=1.0.0,<2.0.0)
Requires-Dist: scikit-learn (>=1.0.0,<2.0.0)
Project-URL: Repository, https://github.com/BorealisAI/group-feature-importance
